_watchdog_fsevents.cpython-310-darwin.so
watchdog/__init__.py
watchdog/events.py
watchdog/version.py
watchdog/watchmedo.py
watchdog/observers/__init__.py
watchdog/observers/api.py
watchdog/observers/fsevents.py
watchdog/observers/fsevents2.py
watchdog/observers/inotify.py
watchdog/observers/inotify_buffer.py
watchdog/observers/inotify_c.py
watchdog/observers/kqueue.py
watchdog/observers/polling.py
watchdog/observers/read_directory_changes.py
watchdog/observers/winapi.py
watchdog/tricks/__init__.py
watchdog/utils/__init__.py
watchdog/utils/bricks.py
watchdog/utils/delayed_queue.py
watchdog/utils/dirsnapshot.py
watchdog/utils/echo.py
watchdog/utils/patterns.py
watchdog/utils/platform.py
watchdog/utils/process_watcher.py
callisto_watchdog-0.0.1.dist-info/AUTHORS
callisto_watchdog-0.0.1.dist-info/COPYING
callisto_watchdog-0.0.1.dist-info/LICENSE
callisto_watchdog-0.0.1.dist-info/METADATA
callisto_watchdog-0.0.1.dist-info/WHEEL
callisto_watchdog-0.0.1.dist-info/entry_points.txt
callisto_watchdog-0.0.1.dist-info/top_level.txt
callisto_watchdog-0.0.1.dist-info/RECORD
