Metadata-Version: 2.1
Name: callisto-watchdog
Version: 0.0.1
Summary: Filesystem events monitoring
Home-page: https://github.com/gorakhargosh/watchdog
Author: OakCityLabs
Author-email: support@callistoapp.com
License: Apache License 2.0
Project-URL: Documentation, https://python-watchdog.readthedocs.io/en/stable/
Project-URL: Source, https://github.com/gorakhargosh/watchdog/
Project-URL: Issues, https://github.com/gorakhargosh/watchdog/issues
Project-URL: Changelog, https://github.com/gorakhargosh/watchdog/blob/master/changelog.rst
Keywords: python filesystem monitoring monitor FSEvents kqueue inotify ReadDirectoryChangesW polling DirectorySnapshot
Classifier: Development Status :: 3 - Alpha
Classifier: Environment :: Console
Classifier: Intended Audience :: Developers
Classifier: Intended Audience :: System Administrators
Classifier: License :: OSI Approved :: Apache Software License
Classifier: Natural Language :: English
Classifier: Operating System :: POSIX :: Linux
Classifier: Operating System :: MacOS :: MacOS X
Classifier: Operating System :: POSIX :: BSD
Classifier: Operating System :: Microsoft :: Windows :: Windows Vista
Classifier: Operating System :: Microsoft :: Windows :: Windows 7
Classifier: Operating System :: Microsoft :: Windows :: Windows 8
Classifier: Operating System :: Microsoft :: Windows :: Windows 8.1
Classifier: Operating System :: Microsoft :: Windows :: Windows 10
Classifier: Operating System :: OS Independent
Classifier: Programming Language :: Python
Classifier: Programming Language :: Python :: 3
Classifier: Programming Language :: Python :: 3 :: Only
Classifier: Programming Language :: Python :: 3.6
Classifier: Programming Language :: Python :: 3.7
Classifier: Programming Language :: Python :: 3.8
Classifier: Programming Language :: Python :: 3.9
Classifier: Programming Language :: Python :: 3.10
Classifier: Programming Language :: Python :: Implementation :: PyPy
Classifier: Programming Language :: C
Classifier: Topic :: Software Development :: Libraries
Classifier: Topic :: System :: Monitoring
Classifier: Topic :: System :: Filesystems
Classifier: Topic :: Utilities
Requires-Python: >=3.6
License-File: LICENSE
License-File: COPYING
License-File: AUTHORS
Provides-Extra: watchmedo
Requires-Dist: PyYAML (>=3.10) ; extra == 'watchmedo'
